logwell/__init__.py
logwell/client.py
logwell/config.py
logwell/errors.py
logwell/py.typed
logwell/queue.py
logwell/source_location.py
logwell/transport.py
logwell/types.py
logwell-0.1.2.dist-info/METADATA
logwell-0.1.2.dist-info/WHEEL
logwell-0.1.2.dist-info/licenses/LICENSE
logwell-0.1.2.dist-info/RECORD
