Metadata-Version: 2.4
Name: logwell
Version: 0.1.2
Summary: Official Python SDK for Logwell logging platform
Project-URL: Homepage, https://github.com/Divkix/Logwell
Project-URL: Documentation, https://github.com/Divkix/Logwell/tree/main/sdks/python#readme
Project-URL: Repository, https://github.com/Divkix/Logwell
Project-URL: Issues, https://github.com/Divkix/Logwell/issues
Author-email: Divkix <divkix@divkix.me>
License-Expression: MIT
License-File: LICENSE
Keywords: logging,logs,logwell,observability,python
Classifier: Development Status :: 4 - Beta
Classifier: Intended Audience :: Developers
Classifier: License :: OSI Approved :: MIT License
Classifier: Operating System :: OS Independent
Classifier: Programming Language :: Python :: 3
Classifier: Programming Language :: Python :: 3.9
Classifier: Programming Language :: Python :: 3.10
Classifier: Programming Language :: Python :: 3.11
Classifier: Programming Language :: Python :: 3.12
Classifier: Programming Language :: Python :: 3.13
Classifier: Typing :: Typed
Requires-Python: >=3.9
Requires-Dist: httpx>=0.25.0
Requires-Dist: typing-extensions>=4.0.0
Provides-Extra: dev
Requires-Dist: coverage[toml]>=7.0.0; extra == 'dev'
Requires-Dist: mypy>=1.8.0; extra == 'dev'
Requires-Dist: pytest-asyncio>=0.23.0; extra == 'dev'
Requires-Dist: pytest-cov>=4.1.0; extra == 'dev'
Requires-Dist: pytest>=8.0.0; extra == 'dev'
Requires-Dist: respx>=0.21.0; extra == 'dev'
Requires-Dist: ruff>=0.4.0; extra == 'dev'
